{
    "textfield": {
        "type": "textfield",
        "description": "Text field",
        "category": "HTML",        
        "scriptName": "genericInput.js",
        "createFunction": "createElementInput",
        "editFunction": "editElementInput"
    },
    "number": {
        "type": "number",
        "description": "Number field",
        "category": "HTML",
        "scriptName": "genericInput.js",
        "createFunction": "createElementInput",
        "editFunction": "editElementInput"
    },
    "password": {
        "type": "password",
        "description": "A password field",
        "category": "HTML",
        "scriptName": "genericInput.js",
        "createFunction": "createElementInput",
        "editFunction": "editElementInput"
    },
    "email": {
        "type": "email",
        "description": "An email field",
        "category": "HTML",
        "scriptName": "genericInput.js",
        "createFunction": "createElementInput",
        "editFunction": "editElementInput"
    },
    "textarea": {
        "type": "textarea",
        "description": "A textarea",
        "category": "HTML",
        "scriptName": "genericInput.js",
        "createFunction": "createElementInput",
        "editFunction": "editElementInput"
    },
    "checkbox": {
        "type": "checkbox",
        "description": "A checkbox",
        "category": "HTML",
        "scriptName": "genericInput.js",
        "createFunction": "createElementInput",
        "editFunction": "editElementInput"
    },
    "radio": {
        "type": "radio",
        "description": "A radio button",
        "category": "HTML",
        "scriptName": "genericInput.js",
        "createFunction": "createElementInput",
        "editFunction": "editElementInput"
    },
    "select": {
        "type": "select",
        "description": "A select",
        "category": "HTML",
        "scriptName": "selectComponent.js",
        "createFunction": "createElementSelect",
        "editFunction": "editElementSelect"
        
    },
    "button": {
        "type": "button",
        "description": "A button",
        "category": "HTML",
        "scriptName": "buttonComponent.js",
        "createFunction": "createElementButton",
        "editFunction": "editElementButton"
        
    },
    "submit": {
        "type": "submit",
        "description": "A submit button",
        "category": "HTML",
        "scriptName": "buttonComponent.js",
        "createFunction": "createElementButton",
        "editFunction": "editElementButton"
        
    },
    "reset": {
        "type": "reset",
        "description": "A reset button",
        "category": "HTML",
        "scriptName": "buttonComponent.js",
        "createFunction": "createElementButton",
        "editFunction": "editElementButton"
        
    },
    "image": {
        "type": "image",
        "description": "Image",
        "category": "HTML",
        "scriptName": "imageComponent.js",
        "createFunction": "createElementImage",
        "editFunction": "editElementImage"

    },
    "file": {
        "type": "file",
        "description": "A file upload",
        "category": "HTML",
        "scriptName": "genericInput.js",
        "createFunction": "createElementInput",
        "editFunction": "editElementInput"
    },
    "hidden": {
        "type": "hidden",
        "description": "A hidden field",
        "category": "HTML",
        "scriptName": "genericInput.js",
        "createFunction": "createElementInput",
        "editFunction": "editElementInput"
    },
    "date": {
        "type": "date",
        "description": "A date field",
        "category": "HTML",
        "scriptName": "genericInput.js",
        "createFunction": "createElementInput",
        "editFunction": "editElementInput"
    
    },
    "datetime": {
        "type": "datetime",
        "description": "A datetime field",
        "category": "HTML",
        "scriptName": "genericInput.js",
        "createFunction": "createElementInput",
        "editFunction": "editElementInput"
    },
   
    "month": {
        "type": "month",
        "description": "A month field",
        "category": "HTML",
        "scriptName": "genericInput.js",
        "createFunction": "createElementInput",
        "editFunction": "editElementInput"
    },
    "week": {
        "type": "week",
        "description": "A week field",
        "category": "HTML",
        "scriptName": "genericInput.js",
        "createFunction": "createElementInput",
        "editFunction": "editElementInput"
    },
    "time": {
        "type": "time",
        "description": "A time field",
        "category": "HTML",
        "scriptName": "genericInput.js",
        "createFunction": "createElementInput",
        "editFunction": "editElementInput"
    },
    "range": {
        "type": "range",
        "description": "A range field",
        "category": "HTML",
        "scriptName": "genericInput.js",
        "createFunction": "createElementInput",
        "editFunction": "editElementInput"
    },
    "color": {
        "type": "color",
        "description": "A color field",
        "category": "HTML",
        "scriptName": "genericInput.js",
        "createFunction": "createElementInput",
        "editFunction": "editElementInput"
    },
    "search": {
        "type": "search",
        "description": "A search field",
        "category": "Bussiness  Logic",
        "scriptName": "genericInput.js",
        "createFunction": "createElementInput",
        "editFunction": "editElementInput"
    },
    "tel": {
        "type": "tel",
        "description": "A telephone field",
        "category": "HTML",
        "scriptName": "genericInput.js",
        "createFunction": "createElementInput",
        "editFunction": "editElementInput"
    },
    "url": {
        "type": "url",
        "description": "A url field",
        "category": "HTML",
        "scriptName": "genericInput.js",
        "createFunction": "createElementInput",
        "editFunction": "editElementInput"
    }, 
    "grid": {
        "type": "grid",
        "description": "HTML Grid",
        "category": "HTML",
        "scriptName": "genericInput.js",
        "createFunction": "createElementInput",
        "editFunction": "editElementInput"
    },
    "dataSet": {
        "type": "dataSet",
        "description": "Data Set",
        "category": "Bussiness  Logic"  ,
        "scriptName": "dataSetComponent.js",
        "createFunction": "createElementDateSet",
        "editFunction": "editElementDataSet"
    },
    "dataGrid": {
        "type": "dataGrid",
        "description": "Data Grid",
        "category": "Bussiness  Logic",
        "scriptName": "dataSetComponent.js",
        "createFunction": "createElementDateSet",
        "editFunction": "editElementDataSet"
    }
}